{
  "updatedAt": "2026-03-08T00:27:19+08:00",
  "market": "TW",
  "currency": "TWD",
  "summary": {
    "totalCost": 979428.5,
    "marketValue": 0.0,
    "unrealizedPnl": -979426.0,
    "realizedPnl": 247738.0,
    "dividendCash": 17500.0,
    "totalPnl": -714188.0,
    "totalPnlPct": -0.7292
  },
  "positions": [
    {
      "symbol": "2330",
      "name": "2330",
      "shares": 1025.0,
      "avgCost": 955.54,
      "lastPrice": 0,
      "priceSource": "NO_DATA",
      "lastPriceAt": "",
      "marketValue": 0.0,
      "unrealizedPnl": -979426.0,
      "realizedPnl": 0.0,
      "dividendCash": 0.0,
      "dividendStockShares": 25.0,
      "totalPnl": -979426.0,
      "totalPnlPct": -1.0
    },
    {
      "symbol": "0050",
      "name": "0050",
      "shares": 0,
      "avgCost": 0,
      "lastPrice": 0,
      "priceSource": "NO_DATA",
      "lastPriceAt": "",
      "marketValue": 0,
      "unrealizedPnl": 0,
      "realizedPnl": 247738.0,
      "dividendCash": 0.0,
      "dividendStockShares": 0.0,
      "totalPnl": 247738.0,
      "totalPnlPct": 0
    },
    {
      "symbol": "0056",
      "name": "0056",
      "shares": 0.0,
      "avgCost": 0,
      "lastPrice": 0,
      "priceSource": "NO_DATA",
      "lastPriceAt": "",
      "marketValue": 0.0,
      "unrealizedPnl": 0.0,
      "realizedPnl": 0.0,
      "dividendCash": 17500.0,
      "dividendStockShares": 0.0,
      "totalPnl": 17500.0,
      "totalPnlPct": 0
    }
  ],
  "trades": [
    {
      "date": "2026-03-07",
      "symbol": "2330",
      "market": "TW",
      "side": "BUY",
      "shares": 1000.0,
      "price": 978.0,
      "amount": 0.0,
      "feeTax": 1426.0,
      "note": "首次建倉"
    },
    {
      "date": "2026-03-10",
      "symbol": "0050",
      "market": "TW",
      "side": "SELL",
      "shares": 500.0,
      "price": 500.0,
      "amount": 0.0,
      "feeTax": 2262.0,
      "note": "分批了結"
    },
    {
      "date": "2026-07-10",
      "symbol": "0056",
      "market": "TW",
      "side": "DIVIDEND_CASH",
      "shares": 0.0,
      "price": 0.0,
      "amount": 17500.0,
      "feeTax": 0.0,
      "note": "每股35元*500股"
    },
    {
      "date": "2026-07-10",
      "symbol": "2330",
      "market": "TW",
      "side": "DIVIDEND_STOCK",
      "shares": 25.0,
      "price": 0.0,
      "amount": 0.0,
      "feeTax": 0.0,
      "note": "配股"
    }
  ]
}